nonebot_plugin_pmhelp/Path.py
nonebot_plugin_pmhelp/__init__.py
nonebot_plugin_pmhelp/draw_help.py
nonebot_plugin_pmhelp/image.py
nonebot_plugin_pmhelp/logger.py
nonebot_plugin_pmhelp/models.py
nonebot_plugin_pmhelp/plugin/manage.py
nonebot_plugin_pmhelp/plugin/model.py
nonebot_plugin_pmhelp/pm_config.py
nonebot_plugin_pmhelp/pmhelp_data/fonts/SourceHanSansCN-Bold.otf
nonebot_plugin_pmhelp/pmhelp_data/fonts/SourceHanSerifCN-Bold.otf
nonebot_plugin_pmhelp/pmhelp_data/fonts/bahnschrift_regular.ttf
nonebot_plugin_pmhelp/pmhelp_data/general/bg.png
nonebot_plugin_pmhelp/pmhelp_data/general/black.png
nonebot_plugin_pmhelp/pmhelp_data/general/black_bord.png
nonebot_plugin_pmhelp/pmhelp_data/general/black_card.png
nonebot_plugin_pmhelp/pmhelp_data/general/blue.png
nonebot_plugin_pmhelp/pmhelp_data/general/blue_bord.png
nonebot_plugin_pmhelp/pmhelp_data/general/blue_card.png
nonebot_plugin_pmhelp/pmhelp_data/general/green.png
nonebot_plugin_pmhelp/pmhelp_data/general/green_bord.png
nonebot_plugin_pmhelp/pmhelp_data/general/green_card.png
nonebot_plugin_pmhelp/pmhelp_data/general/orange.png
nonebot_plugin_pmhelp/pmhelp_data/general/orange_bord.png
nonebot_plugin_pmhelp/pmhelp_data/general/orange_card.png
nonebot_plugin_pmhelp/utils.py
nonebot_plugin_pmhelp/web_api.py
nonebot_plugin_pmhelp/web_page.py
nonebot_plugin_pmhelp-1.4.4.dist-info/LICENSE
nonebot_plugin_pmhelp-1.4.4.dist-info/METADATA
nonebot_plugin_pmhelp-1.4.4.dist-info/WHEEL
nonebot_plugin_pmhelp-1.4.4.dist-info/RECORD
