Metadata-Version: 2.3
Name: nonebot-plugin-pmhelp
Version: 1.4.4
Summary: 源于LittlePaimon的插件管理器插件，提供自动生成帮助图，并对群/私聊进行权限管理
Author: CM-Edelweiss
Author-email: 2633668472@qq.com
Requires-Python: >=3.10,<4.0
Classifier: Programming Language :: Python :: 3
Classifier: Programming Language :: Python :: 3.10
Classifier: Programming Language :: Python :: 3.11
Classifier: Programming Language :: Python :: 3.12
Classifier: Programming Language :: Python :: 3.13
Requires-Dist: Pillow (>=9.1.0,<10.0.0)
Requires-Dist: amis-py-model (>=1.0.0,<2.0.0)
Requires-Dist: fastapi (>=0.93.0)
Requires-Dist: matplotlib (>=3.5.1,<4.0.0)
Requires-Dist: nonebot-adapter-onebot (>=2.1,<3.0)
Requires-Dist: nonebot-plugin-apscheduler (>=0.5.0,<0.6.0)
Requires-Dist: nonebot-plugin-localstore (>=0.7.1,<0.8.0)
Requires-Dist: nonebot-plugin-tortoise-orm (>=0.1.1)
Requires-Dist: nonebot2 (>=2.2.0,<3.0.0)
Requires-Dist: python-jose (>=3.3.0,<4.0.0)
Requires-Dist: ruamel.yaml (>=0.17.21,<0.18.0)
Requires-Dist: tortoise-orm (>=0.19.2,<0.20.0)
Requires-Dist: tqdm (>=4.64.0,<5.0.0)
Requires-Dist: ujson (>=5.4.0,<6.0.0)
